[
  {
    "model": "motor_descuento.disccount",
    "pk": 1,
    "fields": {
      "json_data": {
        "product_id": [
          1,
          2,
          3
        ],
        "retailer_id": [],
        "category_id": [],
        "sub_category_id": [],
        "client_id": null,
        "monto_maximo_orden": -1,
        "es_cliente_prime": false,
        "brand_id": null,
        "dia_promocion": null,
        "contador_descuentos": -1,
        "forma_pago": null,
        "codigo_aplicacion": null
      },
      "monto_maximo": null,
      "monto_actual": 0,
      "fecha_inicio": "2020-02-01",
      "fecha_fin": "2020-12-01",
      "hora_inicio": null,
      "hora_fin": null,
      "prioridad": 2,
      "descuento": 10
    }
  },
  {
    "model": "motor_descuento.disccount",
    "pk": 2,
    "fields": {
      "json_data": {
        "product_id": [
          1,
          2,
          3
        ],
        "retailer_id": [],
        "category_id": [],
        "sub_category_id": [],
        "client_id": null,
        "monto_maximo_orden": -1,
        "es_cliente_prime": false,
        "brand_id": null,
        "dia_promocion": null,
        "contador_descuentos": -1,
        "forma_pago": null,
        "codigo_aplicacion": null
      },
      "monto_maximo": null,
      "monto_actual": 0,
      "fecha_inicio": "2020-02-01",
      "fecha_fin": "2020-12-01",
      "hora_inicio": null,
      "hora_fin": null,
      "prioridad": 1,
      "descuento": 20
    }
  },
  {
    "model": "motor_descuento.disccount",
    "pk": 3,
    "fields": {
      "json_data": {
        "product_id": [],
        "retailer_id": [
          1
        ],
        "category_id": [
          1,
          2,
          3
        ],
        "sub_category_id": [],
        "client_id": null,
        "monto_maximo_orden": -1,
        "es_cliente_prime": false,
        "brand_id": null,
        "dia_promocion": null,
        "contador_descuentos": -1,
        "forma_pago": null,
        "codigo_aplicacion": null
      },
      "monto_maximo": null,
      "monto_actual": 0,
      "fecha_inicio": "2020-01-01",
      "fecha_fin": "2020-01-30",
      "hora_inicio": null,
      "hora_fin": null,
      "prioridad": 4,
      "descuento": 15
    }
  },
  {
    "model": "motor_descuento.disccount",
    "pk": 4,
    "fields": {
      "json_data": {
        "product_id": [],
        "retailer_id": [
          1
        ],
        "category_id": [],
        "sub_category_id": [
          1,
          2,
          3,
          4,
          5
        ],
        "client_id": null,
        "monto_maximo_orden": -1,
        "es_cliente_prime": false,
        "brand_id": null,
        "dia_promocion": null,
        "contador_descuentos": -1,
        "forma_pago": null,
        "codigo_aplicacion": null
      },
      "monto_maximo": null,
      "monto_actual": 0,
      "fecha_inicio": "2019-01-01",
      "fecha_fin": "2019-01-30",
      "hora_inicio": null,
      "hora_fin": null,
      "prioridad": 3,
      "descuento": 28
    }
  },
  {
    "model": "motor_descuento.disccount",
    "pk": 5,
    "fields": {
      "json_data": {
        "product_id": [],
        "retailer_id": [],
        "category_id": [],
        "sub_category_id": [
        ],
        "client_id": [
          1,
          2,
          3
        ],
        "monto_maximo_orden": -1,
        "es_cliente_prime": true,
        "brand_id": null,
        "dia_promocion": null,
        "contador_descuentos": -1,
        "forma_pago": null,
        "codigo_aplicacion": null
      },
      "monto_maximo": null,
      "monto_actual": 0,
      "fecha_inicio": "2019-02-01",
      "fecha_fin": "2019-02-25",
      "hora_inicio": null,
      "hora_fin": null,
      "prioridad": 3,
      "descuento": 41
    }
  },
  {
    "model": "motor_descuento.disccount",
    "pk": 6,
    "fields": {
      "json_data": {
        "product_id": [],
        "retailer_id": [],
        "category_id": [],
        "sub_category_id": [
        ],
        "client_id": [],
        "monto_maximo_orden": -1,
        "es_cliente_prime": false,
        "brand_id": [
          1,
          2,
          3,
          4,
          5
        ],
        "dia_promocion": [],
        "contador_descuentos": -1,
        "forma_pago": null,
        "codigo_aplicacion": null
      },
      "monto_maximo": null,
      "monto_actual": 0,
      "fecha_inicio": "2019-03-01",
      "fecha_fin": "2019-03-25",
      "hora_inicio": null,
      "hora_fin": null,
      "prioridad": 5,
      "descuento": 29
    }
  },
  {
    "model": "motor_descuento.disccount",
    "pk": 7,
    "fields": {
      "json_data": {
        "product_id": [],
        "retailer_id": [],
        "category_id": [],
        "sub_category_id": [
        ],
        "client_id": [],
        "monto_maximo_orden": -1,
        "es_cliente_prime": false,
        "brand_id": [
          1,
          2,
          3,
          4,
          5
        ],
        "dia_promocion": [
          0,
          1,
          2,
          3
        ],
        "contador_descuentos": -1,
        "forma_pago": null,
        "codigo_aplicacion": null
      },
      "monto_maximo": null,
      "monto_actual": 0,
      "fecha_inicio": "2019-04-01",
      "fecha_fin": "2019-04-25",
      "hora_inicio": null,
      "hora_fin": null,
      "prioridad": 7,
      "descuento": 29
    }
  },
  {
    "model": "motor_descuento.disccount",
    "pk": 8,
    "fields": {
      "json_data": {
        "product_id": [],
        "retailer_id": [],
        "category_id": [],
        "sub_category_id": [
        ],
        "client_id": [],
        "monto_maximo_orden": -1,
        "es_cliente_prime": false,
        "brand_id": [
          1,
          2,
          3,
          4,
          5
        ],
        "dia_promocion": [],
        "contador_descuentos": -1,
        "forma_pago": null,
        "codigo_aplicacion": null
      },
      "monto_maximo": null,
      "monto_actual": 0,
      "fecha_inicio": "2019-05-01",
      "fecha_fin": "2019-05-25",
      "hora_inicio": "02:00",
      "hora_fin": "19:00",
      "prioridad": 7,
      "descuento": 29
    }
  },
  {
    "model": "motor_descuento.disccount",
    "pk": 9,
    "fields": {
      "json_data": {
        "product_id": [],
        "retailer_id": [],
        "category_id": [],
        "sub_category_id": [
        ],
        "client_id": [],
        "monto_maximo_orden": -1,
        "es_cliente_prime": false,
        "brand_id": [
          1,
          2,
          3,
          4,
          5
        ],
        "dia_promocion": [],
        "contador_descuentos": -1,
        "forma_pago": null,
        "codigo_aplicacion": "AQ1986"
      },
      "monto_maximo": null,
      "monto_actual": 0,
      "fecha_inicio": "2019-06-01",
      "fecha_fin": "2019-06-28",
      "hora_inicio": "02:00",
      "hora_fin": "19:00",
      "prioridad": 9,
      "descuento": 29
    }
  },
  {
    "model": "motor_descuento.disccount",
    "pk": 10,
    "fields": {
      "json_data": {
        "product_id": [],
        "retailer_id": [],
        "category_id": [],
        "sub_category_id": [
        ],
        "client_id": [],
        "monto_maximo_orden": -1,
        "es_cliente_prime": false,
        "brand_id": [
          1,
          2,
          3,
          4,
          5
        ],
        "dia_promocion": [],
        "contador_descuentos": -1,
        "forma_pago": 3,
        "codigo_aplicacion": null
      },
      "monto_maximo": null,
      "monto_actual": 0,
      "fecha_inicio": "2019-07-01",
      "fecha_fin": "2019-07-28",
      "hora_inicio": "02:00",
      "hora_fin": "19:00",
      "prioridad": 10,
      "descuento": 89
    }
  }
]